{"attribute":"LIGHT","monsterType":"MACHINE","cardType":"EFFECT","level":1,"attackPoint":0,"defencePoint":0,"isSummoned":false,"isDefensive":false,"isReadyToAttack":true,"isPositionChangedInThisTurn":false,"name":"Scanner","price":8000,"isSet":false,"description":"Once per turn, you can select 1 of your opponent\u0027s monsters that is removed from play. Until the End Phase, this card\u0027s name is treated as the selected monster\u0027s name, and this card has the same Attribute, Level, ATK, and DEF as the selected monster. If this card is removed from the field while this effect is applied, remove it from play."}